[
  {
    "name": "Dr. Fazly Ealahi Mamun",
    "designation": "Assistant Professor",
    "profileLink": "https://www.lus.ac.bd/author/mamun/",
    "email": "fazlyealahimamun@lus.ac.bd",
    "phone": "01712153905/01612153905",
    "image": "https://i0.wp.com/www.lus.ac.bd/wp-content/uploads/2015/11/Fazly-Ealahi-Mamun.jpg?fit=464%2C584&ssl=1",
    "qualifications": "",
    "areas": "",
    "publications": ""
  },
  {
    "name": "Dr. Md. Ziaur Rahman",
    "designation": "Assistant ProfessorHead (Acting)",
    "profileLink": "https://www.lus.ac.bd/author/ziaur/",
    "email": "head_ist@lus.ac.bd",
    "phone": "01715610866",
    "image": "https://i0.wp.com/www.lus.ac.bd/wp-content/uploads/2015/11/Ziaur-Rahman.jpg?fit=463%2C580&ssl=1",
    "qualifications": "",
    "areas": "",
    "publications": ""
  },
  {
    "name": "Md. Mamunor Rashid",
    "designation": "Lecturer",
    "profileLink": "https://www.lus.ac.bd/author/mamunor/",
    "email": "mamun_ist@lus.ac.bd",
    "phone": "01728113929",
    "image": "https://i0.wp.com/www.lus.ac.bd/wp-content/uploads/2022/03/Md.-Mamunor-Rashid.jpg?fit=690%2C827&ssl=1",
    "qualifications": "",
    "areas": "",
    "publications": ""
  },
  {
    "name": "Abul Kalam Azad",
    "designation": "Lecturer",
    "profileLink": "https://www.lus.ac.bd/author/abul/",
    "email": "kalam_ist@lus.ac.bd",
    "phone": "01716847584",
    "image": "https://i0.wp.com/www.lus.ac.bd/wp-content/uploads/2019/09/Abul-Kalam-Azad.jpg?fit=431%2C503&ssl=1",
    "qualifications": "",
    "areas": "",
    "publications": ""
  }
]